Workbook

Sheet INPUT
A1: Parameter | B1: Value | C1: Unit
A2: Loan Amount | B2: 500000 | C2: INR
A3: Interest Rate (%) | B3: 0.1 | C3: Annual
A4: Loan Tenure (Years) | B4: 5 | C4: Years
A5: Loan Type | B5: Personal | F5: INPUT sheet → raw inputs
F6: CALCULATIONS sheet → derived values
F7: Amortization table → uses derived values

Sheet CALCULATIONS
A1: Metric | B1: Formula | H1: Metric | I1: Formula | J1: Mathematical Logic
A2: Monthly Interest Rate | B2: =INPUT!B3/12 -> 0.0083333333 | H2: Monthly EMI | I2: =B4 -> 10623.522 | J2: EMI = P × r × (1+r)^n / ((1+r)^n − 1)
A3: Total Months | B3: =INPUT!B4*12 -> 60 | H3: Total Payments | I3: =B4 * B3 -> 637411.34 | J3: Total Payments = EMI × Total Months
A4: EMI | B4: =PMT(INPUT!B3/12, INPUT!B4*12, -INPUT!B2) -> 10623.522 | H4: Total Interest Paid | I4: =SUM(D9:D68) -> 137411.34 | J4: Total Interest = Total Payments − Loan Amount
H5: Total Cost of Loan | I5: =INPUT!B2 + SUM(D9:D68) -> 637411.34 | J5: Total Cost = Loan Amount + Total Interest
B7: Amortization table
A8: Month | B8: Opening Balance | C8: EMI | D8: Interest | E8: Principal | F8: Closing Balance | H8: P = Principal (Loan Amount)
A9: 1 | B9: =INPUT!B2 -> 500000 | C9: =$B$4 -> 10623.522 | D9: =B9 * $B$2 -> 4166.6667 | E9: =C9 - D9 -> 6456.8557 | F9: =B9 - E9 -> 493543.14 | H9: r = Monthly Interest Rate
A10: 2 | B10: =F9 -> 493543.14 | C10: =$B$4 -> 10623.522 | D10: =B10 * $B$2 -> 4112.8595 | E10: =C10 - D10 -> 6510.6628 | F10: =B10 - E10 -> 487032.48 | H10: n = Total Number of Payments
A11: 3 | B11: =F10 -> 487032.48 | C11: =$B$4 -> 10623.522 | D11: =B11 * $B$2 -> 4058.604 | E11: =C11 - D11 -> 6564.9183 | F11: =B11 - E11 -> 480467.56
A12: 4 | B12: =F11 -> 480467.56 | C12: =$B$4 -> 10623.522 | D12: =B12 * $B$2 -> 4003.8964 | E12: =C12 - D12 -> 6619.626 | F12: =B12 - E12 -> 473847.94
A13: 5 | B13: =F12 -> 473847.94 | C13: =$B$4 -> 10623.522 | D13: =B13 * $B$2 -> 3948.7328 | E13: =C13 - D13 -> 6674.7895 | F13: =B13 - E13 -> 467173.15 | H13: Interest_t = OpeningBalance_t × MonthlyRate
A14: 6 | B14: =F13 -> 467173.15 | C14: =$B$4 -> 10623.522 | D14: =B14 * $B$2 -> 3893.1096 | E14: =C14 - D14 -> 6730.4128 | F14: =B14 - E14 -> 460442.73 | H14: Principal_t = EMI − Interest_t
A15: 7 | B15: =F14 -> 460442.73 | C15: =$B$4 -> 10623.522 | D15: =B15 * $B$2 -> 3837.0228 | E15: =C15 - D15 -> 6786.4996 | F15: =B15 - E15 -> 453656.24 | H15: ClosingBalance_t = OpeningBalance_t − Principal_t
A16: 8 | B16: =F15 -> 453656.24 | C16: =$B$4 -> 10623.522 | D16: =B16 * $B$2 -> 3780.4686 | E16: =C16 - D16 -> 6843.0537 | F16: =B16 - E16 -> 446813.18
A17: 9 | B17: =F16 -> 446813.18 | C17: =$B$4 -> 10623.522 | D17: =B17 * $B$2 -> 3723.4432 | E17: =C17 - D17 -> 6900.0792 | F17: =B17 - E17 -> 439913.1
A18: 10 | B18: =F17 -> 439913.1 | C18: =$B$4 -> 10623.522 | D18: =B18 * $B$2 -> 3665.9425 | E18: =C18 - D18 -> 6957.5798 | F18: =B18 - E18 -> 432955.52
A19: 11 | B19: =F18 -> 432955.52 | C19: =$B$4 -> 10623.522 | D19: =B19 * $B$2 -> 3607.9627 | E19: =C19 - D19 -> 7015.5597 | F19: =B19 - E19 -> 425939.96
A20: 12 | B20: =F19 -> 425939.96 | C20: =$B$4 -> 10623.522 | D20: =B20 * $B$2 -> 3549.4997 | E20: =C20 - D20 -> 7074.0227 | F20: =B20 - E20 -> 418865.94
A21: 13 | B21: =F20 -> 418865.94 | C21: =$B$4 -> 10623.522 | D21: =B21 * $B$2 -> 3490.5495 | E21: =C21 - D21 -> 7132.9729 | F21: =B21 - E21 -> 411732.97
A22: 14 | B22: =F21 -> 411732.97 | C22: =$B$4 -> 10623.522 | D22: =B22 * $B$2 -> 3431.1081 | E22: =C22 - D22 -> 7192.4143 | F22: =B22 - E22 -> 404540.55
A23: 15 | B23: =F22 -> 404540.55 | C23: =$B$4 -> 10623.522 | D23: =B23 * $B$2 -> 3371.1713 | E23: =C23 - D23 -> 7252.3511 | F23: =B23 - E23 -> 397288.2
A24: 16 | B24: =F23 -> 397288.2 | C24: =$B$4 -> 10623.522 | D24: =B24 * $B$2 -> 3310.735 | E24: =C24 - D24 -> 7312.7873 | F24: =B24 - E24 -> 389975.41
A25: 17 | B25: =F24 -> 389975.41 | C25: =$B$4 -> 10623.522 | D25: =B25 * $B$2 -> 3249.7951 | E25: =C25 - D25 -> 7373.7272 | F25: =B25 - E25 -> 382601.69
A26: 18 | B26: =F25 -> 382601.69 | C26: =$B$4 -> 10623.522 | D26: =B26 * $B$2 -> 3188.3474 | E26: =C26 - D26 -> 7435.175 | F26: =B26 - E26 -> 375166.51
A27: 19 | B27: =F26 -> 375166.51 | C27: =$B$4 -> 10623.522 | D27: =B27 * $B$2 -> 3126.3876 | E27: =C27 - D27 -> 7497.1348 | F27: =B27 - E27 -> 367669.38
... A67: 59 | B67: =F66 -> 20984.377 | C67: =$B$4 -> 10623.522 | D67: =B67 * $B$2 -> 174.86981 | E67: =C67 - D67 -> 10448.653 | F67: =B67 - E67 -> 10535.725
A68: 60 | B68: =F67 -> 10535.725 | C68: =$B$4 -> 10623.522 | D68: =B68 * $B$2 -> 87.797705 | E68: =C68 - D68 -> 10535.725 | F68: =MAX(B68 - E68,0) -> 0

Sheet DASHBOARD
A1: LOAN CALCULATOR DASHBOARD
D7: Loan Details | F7: Loan Summary | V7: Interest Rate | W7: EMI
V8: 0.08 | W8: =PMT(V8/12, INPUT!$B$4*12, -INPUT!$B$2) -> 10138.197
D9: Loan Amount | E9: =INPUT!B2 -> 500000 | F9: Monthly EMI | H9: =CALCULATIONS!B4 -> 10623.522 | V9: 0.1 | W9: =PMT(V9/12, INPUT!$B$4*12, -INPUT!$B$2) -> 10623.522
D10: Interest Rate | E10: =INPUT!B3 -> 0.1 | F10: Total Interest | H10: =CALCULATIONS!I4 -> 137411.34 | V10: 0.12 | W10: =PMT(V10/12, INPUT!$B$4*12, -INPUT!$B$2) -> 11122.224
D11: Loan Tenure | E11: =INPUT!B4 -> 5 | F11: Total Payment | H11: =CALCULATIONS!I3 -> 637411.34 | V11: 0.14 | W11: =PMT(V11/12, INPUT!$B$4*12, -INPUT!$B$2) -> 11634.125
V39: Interest Rate | W39: EMI | X39: Total Payment | Y39: Total Interest
V40: 0.08 | W40: =PMT(V8/12, INPUT!$B$4*12, -INPUT!$B$2) -> 10138.197 | X40: =W40 * INPUT!$B$4 * 12 -> 608291.83 | Y40: =X40 - INPUT!$B$2 -> 108291.83
V41: 0.1 | W41: =PMT(V9/12, INPUT!$B$4*12, -INPUT!$B$2) -> 10623.522 | X41: =W41 * INPUT!$B$4 * 12 -> 637411.34 | Y41: =X41 - INPUT!$B$2 -> 137411.34
V42: 0.12 | W42: =PMT(V10/12, INPUT!$B$4*12, -INPUT!$B$2) -> 11122.224 | X42: =W42 * INPUT!$B$4 * 12 -> 667333.43 | Y42: =X42 - INPUT!$B$2 -> 167333.43
V43: 0.14 | W43: =PMT(V11/12, INPUT!$B$4*12, -INPUT!$B$2) -> 11634.125 | X43: =W43 * INPUT!$B$4 * 12 -> 698047.53 | Y43: =X43 - INPUT!$B$2 -> 198047.53
D53: Principal | E53: =INPUT!B2 -> 500000
D54: Interest | E54: =CALCULATIONS!I4 -> 137411.34
